prothon/__init__.py
prothon/compiler.py
prothon/generator.py
prothon/proto_base.py
prothon/proto_const.py
prothon/proto_enum.py
prothon/proto_field.py
prothon/proto_message.py
prothon-1.0.0.dist-info/LICENSE
prothon-1.0.0.dist-info/METADATA
prothon-1.0.0.dist-info/WHEEL
prothon-1.0.0.dist-info/top_level.txt
prothon-1.0.0.dist-info/RECORD
