Metadata-Version: 2.1
Name: prothon
Version: 1.0.0
Summary: Generate .proto by .xlsx
Home-page: https://github.com/Fish-Ken/prothon
Author: mousedoc
Author-email: sangyun3631@gmail.com
License: MIT
Platform: UNKNOWN
Classifier: Programming Language :: Python
Classifier: Programming Language :: Python :: 3.6
Classifier: Programming Language :: Python :: 3.7
Classifier: Programming Language :: Python :: 3.8
Classifier: License :: OSI Approved :: MIT License
Classifier: Operating System :: POSIX
Classifier: Operating System :: Microsoft :: Windows
Classifier: Operating System :: MacOS :: MacOS X
